edc_protocol_incident/__init__.py
edc_protocol_incident/action_items.py
edc_protocol_incident/admin_site.py
edc_protocol_incident/apps.py
edc_protocol_incident/auth_objects.py
edc_protocol_incident/auths.py
edc_protocol_incident/choices.py
edc_protocol_incident/constants.py
edc_protocol_incident/list_data.py
edc_protocol_incident/modeladmin_mixins.py
edc_protocol_incident/urls.py
edc_protocol_incident/admin/__init__.py
edc_protocol_incident/admin/protocol_deviation_violation_admin.py
edc_protocol_incident/admin/protocol_incident_admin.py
edc_protocol_incident/form_validators/__init__.py
edc_protocol_incident/form_validators/mixins.py
edc_protocol_incident/form_validators/protocol_deviation_violation_form_validator.py
edc_protocol_incident/form_validators/protocol_incident_form_validator.py
edc_protocol_incident/forms/__init__.py
edc_protocol_incident/forms/protocol_deviation_violation_form.py
edc_protocol_incident/forms/protocol_incident_form.py
edc_protocol_incident/migrations/0001_initial.py
edc_protocol_incident/migrations/0001_squashed_0015_auto_20220927_0401.py
edc_protocol_incident/migrations/0002_auto_20210911_2036.py
edc_protocol_incident/migrations/0003_auto_20211104_1456.py
edc_protocol_incident/migrations/0004_alter_protocoldeviationviolation_violation.py
edc_protocol_incident/migrations/0005_protocolincident_historicalprotocolincident_and_more.py
edc_protocol_incident/migrations/0006_protocolincidents_and_more.py
edc_protocol_incident/migrations/0007_auto_20220704_1841.py
edc_protocol_incident/migrations/0008_alter_historicalprotocoldeviationviolation_action_identifier_and_more.py
edc_protocol_incident/migrations/0009_auto_20220826_0258.py
edc_protocol_incident/migrations/0010_auto_20220826_0322.py
edc_protocol_incident/migrations/0011_auto_20220826_0406.py
edc_protocol_incident/migrations/0012_auto_20220913_2139.py
edc_protocol_incident/migrations/0013_auto_20220927_0349.py
edc_protocol_incident/migrations/0014_auto_20220927_0400.py
edc_protocol_incident-1.0.1.dist-info/licenses/AUTHORS
edc_protocol_incident-1.0.1.dist-info/licenses/LICENSE
edc_protocol_incident-1.0.1.dist-info/METADATA
edc_protocol_incident-1.0.1.dist-info/WHEEL
edc_protocol_incident-1.0.1.dist-info/top_level.txt
edc_protocol_incident-1.0.1.dist-info/RECORD
